mdbutil/loaddb.py
mdbutil/runsql.py
mdbutil-0.1.5.dist-info/METADATA
mdbutil-0.1.5.dist-info/WHEEL
mdbutil-0.1.5.dist-info/entry_points.txt
mdbutil-0.1.5.dist-info/RECORD
