Metadata-Version: 2.1
Name: mdbutil
Version: 0.1.5
Summary: Utilities to run SQL and load a CSV/TSV (gz) file into MariaDB
License: MIT
Author: Eetu Mäkelä
Author-email: eetu.makela@iki.fi
Requires-Python: >=3.7,<4.0
Classifier: License :: OSI Approved :: MIT License
Classifier: Programming Language :: Python :: 3
Classifier: Programming Language :: Python :: 3.7
Classifier: Programming Language :: Python :: 3.8
Classifier: Programming Language :: Python :: 3.9
Classifier: Programming Language :: Python :: 3.10
Classifier: Programming Language :: Python :: 3.11
Classifier: Programming Language :: Python :: 3.12
Requires-Dist: PyMySQL (>=1.0.2,<2.0.0)
Requires-Dist: click (>=8.1.3,<9.0.0)
Requires-Dist: tqdm (>=4.64.0,<5.0.0)
